<?xml version="1.0" encoding="UTF-8" ?>
<!DOCTYPE mapper
  PUBLIC "-//mybatis.org//DTD Mapper 3.0//EN"
  "https://mybatis.org/dtd/mybatis-3-mapper.dtd">
 <mapper namespace="com.footsalhaja.mapper.free.FreeMapper">
 
 	<insert id="insert" >
 	INSERT INTO freeBoard (fb_category, fb_title, fb_content, member_userId)
 	VALUES (#{fb_category}, #{fb_title}, #{fb_content}, #{member_userId})
 	</insert>
 
 	<select id="list" resultType="com.footsalhaja.domain.free.BoardDto">
 	SELECT
 		fb_number,
 		fb_category,
 		fb_title,
 		fb_insertDatetime,
 		member_userId
 	FROM
 		freeBoard
 	WHERE
 		<trim prefixOverrides="OR">
	 		<if test="type == 'all' or type == 'title'">
	 		fb_title LIKE #{keyword}
	 		</if>
	 		
	 		<if test="type == 'all' or type == 'content'">
	 		OR fb_content LIKE #{keyword}
	 		</if>
	 		
	 		<if test="type == 'all' or type == 'writer'">
	 		OR member_userId LIKE #{keyword}
	 		</if>
 		</trim>
 		
 	ORDER BY fb_number DESC
 	LIMIT #{offset}, #{records}
 	</select>
 	
 	<select id="select" resultType="com.footsalhaja.domain.free.BoardDto">
 	SELECT
 		fb_number,
 		fb_category,
 		fb_title,
 		fb_content,
 		fb_insertDatetime,
 		member_userId
 	FROM
 		freeBoard
 	WHERE
 		fb_number = #{fb_number}
 	</select>
 	
 	<update id="update">
 	UPDATE freeBoard
 	SET
 		fb_category = #{fb_category},
 		fb_title = #{fb_title},
 		fb_content = #{fb_content}
 	WHERE
 		fb_number = #{fb_number}
 	</update>
 	
 	<delete id="delete">
 	DELETE FROM freeBoard
 	WHERE fb_number = #{fb_number}
 	</delete>
 	
 	<select id="countAll" resultType="int">
 	SELECT COUNT(*) FROM freeBoard
 	WHERE
 		<trim prefixOverrides="OR">
	 		<if test="type == 'all' or type == 'title'">
	 		fb_title LIKE #{keyword}
	 		</if>
	 		
	 		<if test="type == 'all' or type == 'content'">
	 		OR fb_content LIKE #{keyword}
	 		</if>
	 		
	 		<if test="type == 'all' or type == 'writer'">
	 		OR member_userId LIKE #{keyword}
	 		</if>
 		</trim>
 	</select>
 	
 </mapper>